README.md
setup.py
q4n/__init__.py
q4n/toplevel.py
q4n.egg-info/PKG-INFO
q4n.egg-info/SOURCES.txt
q4n.egg-info/dependency_links.txt
q4n.egg-info/requires.txt
q4n.egg-info/top_level.txt
q4nlib/__init__.py
q4nlib/exploit/__init__.py
q4nlib/exploit/changepasswd.py
q4nlib/exploit/iplist.py
q4nlib/exploit/submitflag.py
q4nlib/exploit/tcpdos.py
q4nlib/interactive/PWN.py
q4nlib/interactive/__init__.py
q4nlib/misc/__init__.py
q4nlib/misc/log.py
q4nlib/misc/q4nctx.py
q4nlib/misc/utf8utils.py
q4nlib/payload/__init__.py
q4nlib/payload/fmt.py
q4nlib/payload/iofile.py
q4nlib/payload/shellcode.py