Metadata-Version: 1.0
Name: q4n
Version: 0.3.1
Summary: my pwntools
Home-page: https://github.com/Q4n/mypwn
Author: Q4n
Author-email: 907659303@qq.com
License: MIT Licence
Keywords: pwn
Platform: linux
